{
    "stats": {
        "max_hp": 60,
        "hp": 60,
        "atk": 1,
        "backward": 0.02,
        "spd": 0.08
    },

    "frames": [
        [
            {
                "x" : 0,
                "y" : 0,
                "width" : 52,
                "height" : 53,
                "delay" : 0.1
            }
        ],
        [
            {
                "x" : 0,
                "y" : 53,
                "width" : 52,
                "height" : 51,
                "delay" : 0.1
            },
            {
                "x" : 55,
                "y" : 53,
                "width" : 52,
                "height" : 51,
                "delay" : 0.1
            }
        ],
        [
            {
                "x" : 0,
                "y" : 106,
                "width" : 52,
                "height" : 53,
                "delay" : 0.1
            },
            {
                "x" : 55,
                "y" : 106,
                "width" : 52,
                "height" : 53,
                "delay" : 0.1
            },
            {
                "x" : 109,
                "y" : 106,
                "width" : 52,
                "height" : 53,
                "delay" : 0.1
            },
            {
                "x" : 162,
                "y" : 106,
                "width" : 52,
                "height" : 53,
                "delay" : 0.1
            }
        ],
        [
            {
                "x" : 0,
                "y" : 161,
                "width" : 52,
                "height" : 51,
                "delay" : 0.1
            },
            {
                "x" : 55,
                "y" : 161,
                "width" : 52,
                "height" : 51,
                "delay" : 0.1
            },
            {
                "x" : 109,
                "y" : 161,
                "width" : 52,
                "height" : 51,
                "delay" : 0.1
            }
        ],
        [
            {
                "x" : 0,
                "y" : 216,
                "width" : 52,
                "height" : 51,
                "delay" : 0.1
            },
            {
                "x" : 55,
                "y" : 216,
                "width" : 52,
                "height" : 51,
                "delay" : 0.1
            },
            {
                "x" : 109,
                "y" : 216,
                "width" : 52,
                "height" : 51,
                "delay" : 0.1
            },
            {
                "x" : 162,
                "y" : 216,
                "width" : 52,
                "height" : 51,
                "delay" : 0.1
            },
            {
                "x" : 216,
                "y" : 216,
                "width" : 52,
                "height" : 51,
                "delay" : 0.1
            },
            {
                "x" : 270,
                "y" : 216,
                "width" : 52,
                "height" : 51,
                "delay" : 0.1
            }
        ]
    ]
}